pyakamai/__init__.py
pyakamai/akamaiapidefinition.py
pyakamai/akamaicasemanagement.py
pyakamai/akamaichinacdn.py
pyakamai/akamaicloudlets.py
pyakamai/akamaicpcode.py
pyakamai/akamaicps.py
pyakamai/akamaidatastream.py
pyakamai/akamaidiagnostictools.py
pyakamai/akamaiedns.py
pyakamai/akamaiehn.py
pyakamai/akamaiksd1.py
pyakamai/akamaiksd2.py
pyakamai/akamailds.py
pyakamai/akamaimsl.py
pyakamai/akamains.py
pyakamai/akamaiproperty.py
pyakamai/akamaipurge.py
pyakamai/akamaireporting.py
pyakamai/akamaiss.py
pyakamai/http_calls.py
pyakamai/pyakamai.py
pyakamai-2.291.dist-info/METADATA
pyakamai-2.291.dist-info/WHEEL
pyakamai-2.291.dist-info/top_level.txt
pyakamai-2.291.dist-info/RECORD
