Metadata-Version: 2.1
Name: pyakamai
Version: 2.291
Summary: A Boto3 like SDK for Akamai
Home-page: https://github.com/Achuthananda/pyakamai
Author: Achuthananda M P
Author-email: achuthadivine@gmail.com
Project-URL: Source, https://github.com/Achuthananda/pyakamai
Keywords: Akamai Python CDN SDK Edge
Classifier: Programming Language :: Python :: 3
Classifier: License :: OSI Approved :: MIT License
Classifier: Operating System :: OS Independent
Classifier: Programming Language :: Python
Classifier: Programming Language :: Python :: 3
Classifier: Programming Language :: Python :: 3.7
Classifier: Programming Language :: Python :: 3.8
Classifier: Programming Language :: Python :: 3.9
Classifier: Programming Language :: Python :: 3.10
Classifier: Programming Language :: Python :: 3.11
Requires-Python: >= 3.7
Requires-Dist: edgegrid-python
Requires-Dist: requests
